sober/__init__.py
sober/_drug_modelling.py
sober/_expectation_propagation.py
sober/_gp.py
sober/_inverse_modelling.py
sober/_kernel.py
sober/_pi.py
sober/_prior.py
sober/_prior_update.py
sober/_rchq.py
sober/_sampler.py
sober/_settings.py
sober/_sober.py
sober/_sober_wrapper.py
sober/_tmvn.py
sober/_utils.py
sober/_weights.py
sober/_wkde.py
sober/BASQ/__init__.py
sober/BASQ/_basq.py
sober/BASQ/_scale_mmlt.py
sober/BOLFI/__init__.py
sober/BOLFI/_botorch_acquisition.py
sober/BOLFI/_gpytorch_bolfi_model.py
sober/FBGP/__init__.py
sober/FBGP/_acquisition_function.py
sober/FBGP/_fitbo.py
sober/FBGP/_fully_Bayesian_gp.py
sober/FBGP/_hyperprior.py
sober/FBGP/_scale_vbq.py
sober/mvnorm/Phi.py
sober/mvnorm/__init__.py
sober/mvnorm/conditioning.py
sober/mvnorm/integration.py
sober/mvnorm/multivariate_normal_cdf.py
sober_bo-2.0.4.dist-info/licenses/LICENSE
sober_bo-2.0.4.dist-info/METADATA
sober_bo-2.0.4.dist-info/WHEEL
sober_bo-2.0.4.dist-info/top_level.txt
sober_bo-2.0.4.dist-info/RECORD
