Metadata-Version: 2.4
Name: sober-bo
Version: 2.0.4
Summary: Fast Bayesian optimization, quadrature, inference over arbitrary domain (discrete and mixed spaces) with GPU parallel acceleration based on GPytorch and BoTorch.
Author-email: Masaki Adachi <masaki@robots.ox.ac.uk>
Maintainer-email: Masaki Adachi <masaki@robots.ox.ac.uk>
License: BSD 3-Clause License
Classifier: Development Status :: 5 - Production/Stable
Classifier: Intended Audience :: Science/Research
Classifier: Topic :: Scientific/Engineering :: Information Analysis
Classifier: License :: OSI Approved :: BSD License
Classifier: Programming Language :: Python :: 3
Requires-Python: >=3.9
License-File: LICENSE
Requires-Dist: botorch>=0.9.5
Requires-Dist: gpytorch>=1.11
Requires-Dist: joblib
Requires-Dist: matplotlib
Requires-Dist: numpy
Requires-Dist: pandas
Requires-Dist: scipy
Requires-Dist: torch>=1.13.1
Dynamic: license-file
